setup.py
karolaz.egg-info/PKG-INFO
karolaz.egg-info/SOURCES.txt
karolaz.egg-info/dependency_links.txt
karolaz.egg-info/top_level.txt
pakiet_testowy/__init__.py
pakiet_testowy/dzialania.py