Metadata-Version: 2.1
Name: karolaz
Version: 1.0
Summary: modul testowy
Home-page: UNKNOWN
License: UNKNOWN
Platform: UNKNOWN
